example/__init__.py
example/math.py
simple_pip_upload-0.0.2.dist-info/LICENSE
simple_pip_upload-0.0.2.dist-info/METADATA
simple_pip_upload-0.0.2.dist-info/WHEEL
simple_pip_upload-0.0.2.dist-info/top_level.txt
simple_pip_upload-0.0.2.dist-info/RECORD
