Metadata-Version: 2.1
Name: simple-pip-upload
Version: 0.0.2
Summary: 一个简单的四则运算 PyPI 上传例子
Home-page: https://simple_pip_upload.xx
Author: moumoubaimifan
Author-email: example@example.com
License: UNKNOWN
Platform: UNKNOWN
Classifier: Programming Language :: Python :: 3
Classifier: License :: OSI Approved :: MIT License
Classifier: Operating System :: OS Independent
